LICENSE.md
MANIFEST.in
README.md
requirements.txt
setup.py
duplex_tools/__init__.py
duplex_tools/assess_split_on_adapter.py
duplex_tools/dorado_stereo.sh
duplex_tools/filter_pairs.py
duplex_tools/pair.py
duplex_tools/pairs_from_summary.py
duplex_tools/split_on_adapter.py
duplex_tools/split_pairs.py
duplex_tools/split_pairs_steps.py
duplex_tools/split_pairs_utils.py
duplex_tools/utils.py
duplex_tools.egg-info/PKG-INFO
duplex_tools.egg-info/SOURCES.txt
duplex_tools.egg-info/dependency_links.txt
duplex_tools.egg-info/entry_points.txt
duplex_tools.egg-info/requires.txt
duplex_tools.egg-info/top_level.txt
duplex_tools.egg-info/zip-safe