Metadata-Version: 2.1
Name: duplex-tools
Version: 0.3.2
Summary: Range of tools to support operations on Duplex Sequencing read pairs.
Home-page: https://github.com/nanoporetech/duplex-tools
Author: ont-research
Author-email: ont-research@nanoporetech.com
License: UNKNOWN
Platform: UNKNOWN
License-File: LICENSE.md
